MANIFEST.in
setup.py
ywAUT/Devices.py
ywAUT/Devices_s.py
ywAUT/Devices_stf.py
ywAUT/Driver.py
ywAUT/Globalvar.py
ywAUT/ReadConfig.py
ywAUT/__init__.py
ywAUT/__main__.py
ywAUT/project/config.ini
ywAUT/project/steps/common_steps.py
ywAUT/project/steps/demo.py
ywAUT/project/testsuite/demo.feature
yw_AUT.egg-info/PKG-INFO
yw_AUT.egg-info/SOURCES.txt
yw_AUT.egg-info/dependency_links.txt
yw_AUT.egg-info/requires.txt
yw_AUT.egg-info/top_level.txt