Metadata-Version: 1.0
Name: yw-AUT
Version: 0.0.6
Summary: An feature extraction algorithm
Home-page: http://git.code.oa.com/yuewen-test/u2_stf_automator.git
Author: HanJieFeng
Author-email: hanjiefeng1987@126.com
License: MIT Licence
Keywords: pip,SICA,featureextraction
Platform: any
